vortex_array-0.32.0.dist-info/METADATA
vortex_array-0.32.0.dist-info/WHEEL
vortex/arrow/expression.py
vortex/py.typed
vortex/_lib/dtype.pyi
vortex/_lib/__init__.pyi
vortex/_lib/iter.pyi
vortex/_lib/scalar.pyi
vortex/_lib/file.pyi
vortex/_lib/io.pyi
vortex/_lib/arrays.pyi
vortex/_lib/expr.pyi
vortex/_lib/compress.pyi
vortex/_lib/serde.pyi
vortex/_lib/registry.pyi
vortex/_lib/dataset.pyi
vortex/_lib/mypy.allowlist
vortex/serde.py
vortex/expr.py
vortex/arrays.py
vortex/substrait.py
vortex/dataset.py
vortex/polars_.py
vortex/io.py
vortex/file.py
vortex/__init__.py
vortex/_lib.abi3.so
vortex_array-0.32.0.dist-info/RECORD
