Metadata-Version: 2.4
Name: vortex-array
Version: 0.32.0
Requires-Dist: pyarrow>=17.0.0
Requires-Dist: substrait>=0.23.0
Requires-Dist: polars>=1.27.0 ; extra == 'polars'
Requires-Dist: pandas>=2.2.0 ; extra == 'pandas'
Requires-Dist: numpy>=1.26.0 ; extra == 'numpy'
Requires-Dist: duckdb>=1.1.2 ; extra == 'duckdb'
Provides-Extra: polars
Provides-Extra: pandas
Provides-Extra: numpy
Provides-Extra: duckdb
Summary: Python bindings for Vortex, an Apache Arrow-compatible toolkit for working with compressed array data.
Keywords: vortex
Home-Page: https://github.com/spiraldb/vortex
Author: Vortex Authors <hello@vortex.dev>
Author-email: Vortex Authors <hello@vortex.dev>
License: Apache-2.0
Requires-Python: >=3.10
Project-URL: Documentation, https://docs.vortex.dev
Project-URL: Changelog, https://github.com/spiraldb/vortex/blob/develop/CHANGELOG.md
Project-URL: Issues, https://github.com/spiraldb/vortex/issues
Project-URL: Benchmarks, https://bench.vortex.dev
